rsb/__init__.py
rsb/py.typed
rsb/adapters/__init__.py
rsb/adapters/adapter.py
rsb/collections/__init__.py
rsb/collections/readonly_collection.py
rsb/collections/writable_colection.py
rsb/containers/__init__.py
rsb/containers/failure.py
rsb/containers/maybe.py
rsb/containers/result.py
rsb/containers/success.py
rsb/contracts/__init__.py
rsb/contracts/maybe_protocol.py
rsb/contracts/repositories/__init__.py
rsb/contracts/repositories/deletable.py
rsb/contracts/repositories/readable.py
rsb/contracts/repositories/updatable.py
rsb/contracts/repositories/writable.py
rsb/coroutines/__init__.py
rsb/coroutines/fire_and_forget.py
rsb/coroutines/run_async.py
rsb/coroutines/run_sync.py
rsb/decorators/__init__.py
rsb/decorators/entities.py
rsb/decorators/requires_module.py
rsb/decorators/services.py
rsb/decorators/value_objects.py
rsb/functions/__init__.py
rsb/functions/bytes2mime.py
rsb/functions/create_instance_dynamically.py
rsb/functions/ext2mime.py
rsb/functions/mime2ext.py
rsb/functions/schema2basemodel.py
rsb/functions/files/__init__.py
rsb/functions/files/find_extension.py
rsb/functions/files/get_extension_agressivelly.py
rsb/functions/files/get_extension_from_filename.py
rsb/functions/files/get_extension_from_url.py
rsb/json/__init__.py
rsb/json/json_schema_builder.py
rsb/json/unsuported_type_error.py
rsb/models/__init__.py
rsb/models/alias_choices.py
rsb/models/any_url.py
rsb/models/base64str.py
rsb/models/base_model.py
rsb/models/config_dict.py
rsb/models/create_model.py
rsb/models/field.py
rsb/models/mimetype.py
rsb/models/model_validator.py
rsb/models/private_attr.py
rsb/models/url_constraints.py
rsb/models/functions/__init__.py
rsb/models/functions/schema_to_model.py
rock_solid_base-0.1.14.dist-info/METADATA
rock_solid_base-0.1.14.dist-info/WHEEL
rock_solid_base-0.1.14.dist-info/RECORD
