Metadata-Version: 2.4
Name: rock-solid-base
Version: 0.1.14
Summary: Add your description here
Author-email: Arthur Brenno <64020210+arthurbrenno@users.noreply.github.com>
Requires-Python: >=3.13
Requires-Dist: pydantic>=2.11.3
